[
	{
		"title": "热门景点",
		"site1": "龙门石窟",
		"imgSrc": "../images/hot-img1.jpg",
		"user1": "6812585529：",
		"word1": "“环境很好，东西也很便宜。每一个佛像后面都有一个故事，如果只是看一眼就走，太可惜了。只是好多的头像...",
		"site2": "白马寺",
		"user2": "想1988：",
		"word2": "“来到白马寺，一定要去看一下白马寺八景，我记得有角楼，石马，马寺钟声，清凉台，还有个什么叫焚经台，不过我没有在景点..."
	},
	{
		"title": "必尝美食",
		"site1": "张记烧鸡",
		"imgSrc": "../images/hot-img2.jpg",
		"word1": "很多地方有烧鸡这道菜，做烧鸡的也有很多，可是做烧鸡能做出名的很少，能闻名全国的更...",
		"site2": "洛阳不翻汤"
	},
	{
		"title": "热门购物",
		"site1": "丹尼斯（栾川店）",
		"imgSrc": "../images/hot-img3.jpg",
		"word1": "丹尼斯位于位于县区中心繁华地段兴华路中段，是一家大型的购物百货大卖场，卖场内有百...",
		"site2": "时代广场（栾川县卫生局西南）",
		"word2": "时代广场是县城最好的购物广场了，位于中心商圈，以吃饭为主，大多数品牌店也有很大的打折力..."
	}
]